{ "compressionlevel":-1,
 "height":16,
 "infinite":false,
 "layers":[
        {
         "draworder":"topdown",
         "id":2,
         "name":"Object Layer 1",
         "objects":[
                {
                 "height":80,
                 "id":1,
                 "name":"obj_wall",
                 "rotation":0,
                 "type":"",
                 "visible":true,
                 "width":224,
                 "x":0,
                 "y":192
                }, 
                {
                 "height":16,
                 "id":2,
                 "name":"obj_wall",
                 "rotation":0,
                 "type":"",
                 "visible":true,
                 "width":192,
                 "x":32,
                 "y":176
                }, 
                {
                 "height":16,
                 "id":3,
                 "name":"obj_wall",
                 "rotation":0,
                 "type":"",
                 "visible":true,
                 "width":112,
                 "x":48,
                 "y":160
                }, 
                {
                 "height":16,
                 "id":4,
                 "name":"obj_wall",
                 "rotation":0,
                 "type":"",
                 "visible":true,
                 "width":80,
                 "x":64,
                 "y":144
                }, 
                {
                 "height":16,
                 "id":5,
                 "name":"oCrate",
                 "properties":[
                        {
                         "name":"item",
                         "type":"string",
                         "value":"obj_hpup"
                        }],
                 "rotation":0,
                 "type":"",
                 "visible":true,
                 "width":16,
                 "x":80,
                 "y":96
                }, 
                {
                 "height":16,
                 "id":6,
                 "name":"oCrate",
                 "rotation":0,
                 "type":"",
                 "visible":true,
                 "width":16,
                 "x":96,
                 "y":96
                }, 
                {
                 "height":16,
                 "id":7,
                 "name":"oCrate",
                 "rotation":0,
                 "type":"",
                 "visible":true,
                 "width":16,
                 "x":112,
                 "y":96
                }, 
                {
                 "height":16,
                 "id":8,
                 "name":"obj_enemy",
                 "rotation":0,
                 "type":"",
                 "visible":true,
                 "width":16,
                 "x":72,
                 "y":136
                }, 
                {
                 "height":16,
                 "id":9,
                 "name":"obj_enemy",
                 "properties":[
                        {
                         "name":"chance",
                         "type":"float",
                         "value":0.25
                        }],
                 "rotation":0,
                 "type":"",
                 "visible":true,
                 "width":16,
                 "x":112,
                 "y":88
                }],
         "opacity":1,
         "type":"objectgroup",
         "visible":false,
         "x":0,
         "y":0
        }, 
        {
         "draworder":"topdown",
         "id":3,
         "name":"Copy of Object Layer 1",
         "objects":[
                {
                 "height":80,
                 "id":10,
                 "name":"obj_wall",
                 "rotation":0,
                 "type":"",
                 "visible":true,
                 "width":224,
                 "x":0,
                 "y":192
                }, 
                {
                 "height":16,
                 "id":11,
                 "name":"obj_wall",
                 "rotation":0,
                 "type":"",
                 "visible":true,
                 "width":192,
                 "x":32,
                 "y":176
                }, 
                {
                 "height":32,
                 "id":13,
                 "name":"obj_wall",
                 "rotation":0,
                 "type":"",
                 "visible":true,
                 "width":128,
                 "x":32,
                 "y":144
                }, 
                {
                 "height":16,
                 "id":14,
                 "name":"oCrate",
                 "properties":[
                        {
                         "name":"item",
                         "type":"string",
                         "value":"obj_hpup"
                        }],
                 "rotation":0,
                 "type":"",
                 "visible":true,
                 "width":16,
                 "x":112,
                 "y":96
                }, 
                {
                 "height":16,
                 "id":15,
                 "name":"oCrate",
                 "rotation":0,
                 "type":"",
                 "visible":true,
                 "width":16,
                 "x":128,
                 "y":96
                }, 
                {
                 "height":16,
                 "id":16,
                 "name":"oCrate",
                 "rotation":0,
                 "type":"",
                 "visible":true,
                 "width":16,
                 "x":144,
                 "y":96
                }, 
                {
                 "height":16,
                 "id":17,
                 "name":"obj_enemy",
                 "rotation":0,
                 "type":"",
                 "visible":true,
                 "width":16,
                 "x":40,
                 "y":136
                }, 
                {
                 "height":16,
                 "id":18,
                 "name":"obj_enemy",
                 "properties":[
                        {
                         "name":"chance",
                         "type":"float",
                         "value":0.25
                        }],
                 "rotation":0,
                 "type":"",
                 "visible":true,
                 "width":16,
                 "x":128,
                 "y":88
                }, 
                {
                 "height":16,
                 "id":19,
                 "name":"obj_platform",
                 "rotation":0,
                 "type":"",
                 "visible":true,
                 "width":16,
                 "x":16,
                 "y":144
                }, 
                {
                 "height":16,
                 "id":20,
                 "name":"obj_wall",
                 "rotation":0,
                 "type":"",
                 "visible":true,
                 "width":16,
                 "x":160,
                 "y":160
                }],
         "opacity":1,
         "type":"objectgroup",
         "visible":true,
         "x":0,
         "y":0
        }],
 "nextlayerid":4,
 "nextobjectid":22,
 "orientation":"orthogonal",
 "renderorder":"right-down",
 "tiledversion":"1.4.3",
 "tileheight":16,
 "tilesets":[],
 "tilewidth":16,
 "type":"map",
 "version":1.4,
 "width":14
}